roark_analytics/__init__.py
roark_analytics/_base_client.py
roark_analytics/_client.py
roark_analytics/_compat.py
roark_analytics/_constants.py
roark_analytics/_exceptions.py
roark_analytics/_files.py
roark_analytics/_models.py
roark_analytics/_qs.py
roark_analytics/_resource.py
roark_analytics/_response.py
roark_analytics/_streaming.py
roark_analytics/_types.py
roark_analytics/_version.py
roark_analytics/py.typed
roark_analytics/_utils/__init__.py
roark_analytics/_utils/_compat.py
roark_analytics/_utils/_datetime_parse.py
roark_analytics/_utils/_logs.py
roark_analytics/_utils/_proxy.py
roark_analytics/_utils/_reflection.py
roark_analytics/_utils/_resources_proxy.py
roark_analytics/_utils/_streams.py
roark_analytics/_utils/_sync.py
roark_analytics/_utils/_transform.py
roark_analytics/_utils/_typing.py
roark_analytics/_utils/_utils.py
roark_analytics/lib/.keep
roark_analytics/resources/__init__.py
roark_analytics/resources/call.py
roark_analytics/resources/evaluation.py
roark_analytics/resources/health.py
roark_analytics/resources/integrations.py
roark_analytics/resources/metric.py
roark_analytics/resources/persona.py
roark_analytics/resources/simulation.py
roark_analytics/types/__init__.py
roark_analytics/types/call_create_params.py
roark_analytics/types/call_create_response.py
roark_analytics/types/call_get_by_id_response.py
roark_analytics/types/call_get_evaluation_runs_response.py
roark_analytics/types/call_get_metrics_params.py
roark_analytics/types/call_get_metrics_response.py
roark_analytics/types/call_get_sentiment_runs_response.py
roark_analytics/types/evaluation_create_job_params.py
roark_analytics/types/evaluation_create_job_response.py
roark_analytics/types/evaluation_get_evaluator_by_id_response.py
roark_analytics/types/evaluation_get_evaluators_params.py
roark_analytics/types/evaluation_get_evaluators_response.py
roark_analytics/types/evaluation_get_job_response.py
roark_analytics/types/evaluation_get_job_runs_params.py
roark_analytics-2.13.0.dist-info/METADATA
roark_analytics-2.13.0.dist-info/WHEEL
roark_analytics-2.13.0.dist-info/licenses/LICENSE
roark_analytics-2.13.0.dist-info/RECORD
